[{"Pressed": "Key.shift"}, {"Held": "Key.shift"}, {"Held": "'M'"}, {"Released": "'M'"}, {"Released": "Key.shift"}, {"Pressed": "'y'"}, {"Held": "'y'"}, {"Released": "'y'"}, {"Pressed": "Key.space"}, {"Held": "Key.space"}, {"Released": "Key.space"}, {"Pressed": "'n'"}, {"Held": "'n'"}, {"Released": "'n'"}, {"Pressed": "'a'"}, {"Held": "'a'"}, {"Released": "'a'"}, {"Pressed": "'m'"}, {"Held": "'m'"}, {"Released": "'m'"}, {"Pressed": "'e'"}, {"Held": "'e'"}, {"Released": "'e'"}, {"Pressed": "'i'"}, {"Held": "'i'"}, {"Released": "'i'"}, {"Pressed": "'s'"}, {"Held": "'s'"}, {"Released": "'s'"}, {"Pressed": "Key.space"}, {"Held": "Key.space"}, {"Released": "Key.space"}, {"Pressed": "Key.shift"}, {"Held": "Key.shift"}, {"Held": "'T'"}, {"Released": "'T'"}, {"Released": "Key.shift"}, {"Pressed": "'.'"}, {"Held": "'.'"}, {"Released": "'.'"}, {"Pressed": "'y'"}, {"Held": "'y'"}, {"Released": "'y'"}, {"Pressed": "'u'"}, {"Held": "'u'"}, {"Released": "'u'"}, {"Pressed": "'v'"}, {"Held": "'v'"}, {"Released": "'v'"}, {"Pressed": "'a'"}, {"Held": "'a'"}, {"Released": "'a'"}]